testbrain/__init__.py
testbrain/__main__.py
testbrain/client/__init__.py
testbrain/client/auth.py
testbrain/client/client.py
testbrain/commands/__init__.py
testbrain/commands/deployment.py
testbrain/commands/initializer.py
testbrain/commands/license.py
testbrain/commands/project.py
testbrain/core/__init__.py
testbrain/core/app.py
testbrain/core/config.py
testbrain/core/exceptions.py
testbrain/core/state.py
testbrain/helpers/__init__.py
testbrain/helpers/deployments.py
testbrain/helpers/fs.py
testbrain/helpers/installers.py
testbrain/helpers/misc.py
testbrain/helpers/options.py
testbrain/helpers/params.py
testbrain/helpers/structures.py
testbrain/helpers/validators.py
testbrain/templates/docker-compose.yml-tpl
testbrain/templates/postgresql.conf-tpl
testbrain/templates/script.py-tpl
testbrain-1.1.0rc2.dist-info/METADATA
testbrain-1.1.0rc2.dist-info/WHEEL
testbrain-1.1.0rc2.dist-info/entry_points.txt
testbrain-1.1.0rc2.dist-info/top_level.txt
testbrain-1.1.0rc2.dist-info/RECORD
